cwhy/__init__.py
cwhy/__main__.py
cwhy/clangd_lsp_integration.py
cwhy/cwhy.py
cwhy/explain.py
cwhy/functions.py
cwhy/git_integration.py
cwhy/prompts.py
cwhy/utils.py
cwhy-0.6.dist-info/METADATA
cwhy-0.6.dist-info/WHEEL
cwhy-0.6.dist-info/entry_points.txt
cwhy-0.6.dist-info/licenses/LICENSE
cwhy-0.6.dist-info/RECORD
