Metadata-Version: 2.4
Name: cwhy
Version: 0.6
Summary: Explains and proposes fixes for compile-time errors for many programming languages.
Project-URL: Homepage, https://github.com/plasma-umass/cwhy
Project-URL: Bug Tracker, https://github.com/plasma-umass/cwhy/issues
Author-email: Emery Berger <emery.berger@gmail.com>, Nicolas van Kempen <nvankemp@gmail.com>
License-File: LICENSE
Classifier: License :: OSI Approved :: Apache Software License
Classifier: Operating System :: OS Independent
Classifier: Programming Language :: Python :: 3
Requires-Python: >=3.9
Requires-Dist: llm-utils>=0.2.8
Requires-Dist: openai>=1.84.0
Requires-Dist: rich>=13.7.1
